canarytools/__init__.py
canarytools/console.py
canarytools/exceptions.py
canarytools/models/__init__.py
canarytools/models/base.py
canarytools/models/canarytokens.py
canarytools/models/databundles.py
canarytools/models/devices.py
canarytools/models/flocks.py
canarytools/models/incidents.py
canarytools/models/result.py
canarytools/models/settings.py
canarytools/models/update.py
canarytools-1.1.1.dist-info/LICENSE.txt
canarytools-1.1.1.dist-info/METADATA
canarytools-1.1.1.dist-info/WHEEL
canarytools-1.1.1.dist-info/top_level.txt
canarytools-1.1.1.dist-info/RECORD
