Metadata-Version: 2.1
Name: canarytools
Version: 1.1.1
Summary: An API for the Thinkst Canary Console
Home-page: https://canary.tools/
Author: Thinkst Applied Research
Author-email: canary@thinkst.com
License: Revised BSD License
Keywords: canary thinkst canarytools api wrapper
Platform: UNKNOWN
Classifier: Development Status :: 5 - Production/Stable
Classifier: Intended Audience :: Developers
Classifier: Topic :: Software Development :: Build Tools
Classifier: License :: OSI Approved :: BSD License
Classifier: Natural Language :: English
Classifier: Programming Language :: Python :: 2
Classifier: Programming Language :: Python :: 2.7
Classifier: Programming Language :: Python :: 3
Classifier: Programming Language :: Python :: 3.3
Classifier: Programming Language :: Python :: 3.4
Classifier: Programming Language :: Python :: 3.5
Classifier: Programming Language :: Python :: 3.6
Classifier: Topic :: Utilities
Requires-Dist: requests (>=2.10.0)
Requires-Dist: python-dateutil (>=2.1)
Requires-Dist: pytz (>=2013b)
